mebula/__init__.py
mebula/azure.py
mebula/dict_filter.py
mebula/google.py
mebula/oracle.py
mebula/py.typed
mebula-0.2.10.dist-info/LICENSES/CC0-1.0.txt
mebula-0.2.10.dist-info/LICENSES/MIT.txt
mebula-0.2.10.dist-info/METADATA
mebula-0.2.10.dist-info/WHEEL
mebula-0.2.10.dist-info/RECORD
