Metadata-Version: 2.1
Name: mebula
Version: 0.2.10
Summary: 
Home-page: https://github.com/milliams/mebula
License: MIT
Author: Matt Williams
Author-email: matt@milliams.com
Requires-Python: >=3.8.0,<4.0.0
Classifier: License :: OSI Approved :: MIT License
Classifier: Programming Language :: Python :: 3
Classifier: Programming Language :: Python :: 3.8
Classifier: Programming Language :: Python :: 3.9
Classifier: Programming Language :: Python :: 3.10
Classifier: Programming Language :: Python :: 3.11
Classifier: Programming Language :: Python :: 3.12
Provides-Extra: azure
Provides-Extra: google
Provides-Extra: oracle
Requires-Dist: azure-identity (>=1.6.0,<2.0.0) ; extra == "azure"
Requires-Dist: azure-mgmt-compute (>=21,<28) ; extra == "azure"
Requires-Dist: google-api-python-client (>=1.7.11,<3.0.0) ; extra == "google"
Requires-Dist: lark (>=1.0,<2.0) ; extra == "google"
Requires-Dist: oci (>=2.10.0,<3.0.0) ; extra == "oracle"
Project-URL: Repository, https://github.com/milliams/mebula
